{
  "0" : {
    "location": "Tromso +1",
    "UTC": 1
  },
  "1": {
    "location": "Oslo +1",
    "UTC": 1
  },
  "2": {
    "location": "Liege +1",
    "UTC": 1
  },
  "3": {
    "location": "Paris +1",
    "UTC": 1
  },
  "4": {
    "location": "Marseille +1",
    "UTC": 1
  },
  "5": {
    "location": "Madrid +1",
    "UTC": 1
  },
  "6": {
    "location": "Marrakech +1",
    "UTC": 1
  },
  "7": {
    "location": "Agadez +1",
    "UTC": 1
  },
  "8": {
    "location": "Libreville +1",
    "UTC": 1
  },
  "9": {
    "location": "Luanda +1",
    "UTC": 1
  },
  "10": {
    "location": "Helsinki +2",
    "UTC": 2
  },
  "11": {
    "location": "Kiev +2",
    "UTC": 2
  },
  "12": {
    "location": "Tripoli +2",
    "UTC": 2
  },
  "13": {
    "location": "Khartoum +2",
    "UTC": 2
  },
  "14": {
    "location": "Windhoek +2",
    "UTC": 2
  },
  "15": {
    "location": "Cape Town +2",
    "UTC": 2
  },
  "16": {
    "location": "Moscou +3",
    "UTC": 3
  },
  "17": {
    "location": "Istanbul +3",
    "UTC": 3
  },
  "18": {
    "location": "Medine +3",
    "UTC": 3
  },
  "19": {
    "location": "Nairobi +3",
    "UTC": 3
  },
  "20": {
    "location": "Tananarive +3",
    "UTC": 3
  },
  "21": {
    "location": "Iekaterinbourg +5",
    "UTC": 5
  },
  "22": {
    "location": "Samarcande +5",
    "UTC": 5
  },
  "23": {
    "location": "Karaganda +6",
    "UTC": 6
  },
  "24": {
    "location": "Dhaka +6",
    "UTC": 6
  },
  "25": {
    "location": "Krasnoyarsk +7",
    "UTC": 7
  },
  "26": {
    "location": "Bangkok +7",
    "UTC": 7
  },
  "27": {
    "location": "Jakarta +7",
    "UTC": 7
  },
  "28": {
    "location": "Hong kong +8",
    "UTC": 8
  },
  "29": {
    "location": "Perth +8",
    "UTC": 8
  },
  "30": {
    "location": "Reykjavik +0",
    "UTC": 0
  },
  "31": {
    "location": "Nouakchott +0",
    "UTC": 0
  },
  "32": {
    "location": "Conakry +0",
    "UTC": 0
  },
  "33": {
    "location": "Paramaribo -3",
    "UTC": -3
  },
  "34": {
    "location": "Fortaleza -3",
    "UTC": -3
  },
  "35": {
    "location": "Rio -3",
    "UTC": -3
  },
  "36": {
    "location": "Montevideo -3",
    "UTC": -3
  },
  "37": {
    "location": "Postville -4",
    "UTC": -4
  },
  "38": {
    "location": "Caracas -4",
    "UTC": -4
  },
  "39": {
    "location": "La Paz -4",
    "UTC": -4
  },
  "40": {
    "location": "Quebec -5",
    "UTC": -5
  },
  "41": {
    "location": "Washington -5",
    "UTC": -5
  },
  "42": {
    "location": "Miami -5",
    "UTC": -5
  },
  "43": {
    "location": "Kingston -5",
    "UTC": -5
  },
  "44": {
    "location": "Bogota -5",
    "UTC": -5
  },
  "45": {
    "location": "Lima -5",
    "UTC": -5
  },
  "46": {
    "location": "Winnipeg -6",
    "UTC": -6
  },
  "47": {
    "location": "Chicago -6",
    "UTC": -6
  },
  "48": {
    "location": "Dalas -6",
    "UTC": -6
  },
  "49": {
    "location": "Mexico -6",
    "UTC": -6
  },
  "50": {
    "location": "Managua -6",
    "UTC": -6
  },
  "51": {
    "location": "Edmonton -7",
    "UTC": -7
  },
  "52": {
    "location": "Denver -7",
    "UTC": -7
  },
  "53": {
    "location": "Vancouver -8",
    "UTC": 8
  },
  "54": {
    "location": "Los Angeles -8",
    "UTC": -8
  }
}